{
  "items1":[
       {
      "itemID":"1",
      "itemTitle":"Jeans",
      "itemCount":0,
      "itemPrice":25.0
      
    },
       {
      "itemID":"2",
      "itemTitle":"T-Shirt",
      "itemCount":0,
      "itemPrice":25.0
      
    },
       {
      "itemID":"3",
      "itemTitle":"Jeans",
      "itemCount":0,
      "itemPrice":25.0
      
    },
       {
      "itemID":"4",
      "itemTitle":"Jeans",
      "itemCount":0,
      "itemPrice":25.0
      
    },
       {
      "itemID":"5",
      "itemTitle":"Jeans",
      "itemCount":0,
      "itemPrice":25.0
      
    },
       {
      "itemID":"6",
      "itemTitle":"Jeans",
      "itemCount":0,
      "itemPrice":25.0
      
    },
       {
      "itemID":"7",
      "itemTitle":"Jeans",
      "itemCount":0,
      "itemPrice":25.0
      
    }
       
    ],
  "items2":[
       {
      "itemID":"11",
      "itemTitle":"Jeans",
      "itemCount":0,
      "itemPrice":25.0
      
    },
       {
      "itemID":"12",
      "itemTitle":"T-Shirt",
      "itemCount":0,
      "itemPrice":25.0
      
    },
       {
      "itemID":"13",
      "itemTitle":"Jeans",
      "itemCount":0,
      "itemPrice":25.0
      
    },
       {
      "itemID":"14",
      "itemTitle":"Jeans",
      "itemCount":0,
      "itemPrice":25.0
      
    },
       {
      "itemID":"15",
      "itemTitle":"Jeans",
      "itemCount":0,
      "itemPrice":25.0
      
    },
       {
      "itemID":"16",
      "itemTitle":"Jeans",
      "itemCount":0,
      "itemPrice":25.0
      
    },
       {
      "itemID":"17",
      "itemTitle":"Jeans",
      "itemCount":0,
      "itemPrice":25.0
      
    }
       
    ]

}
